LICENSE
polybar_clockify/__init__.py
polybar_clockify/api.py
polybar_clockify/app.py
polybar_clockify/objects.py
polybar_clockify/settings.py
polybar_clockify/utils.py
polybar_clockify-0.2.8.dist-info/entry_points.txt
polybar_clockify-0.2.8.dist-info/LICENSE
polybar_clockify-0.2.8.dist-info/WHEEL
polybar_clockify-0.2.8.dist-info/METADATA
polybar_clockify-0.2.8.dist-info/RECORD
