Metadata-Version: 2.1
Name: polybar-clockify
Version: 0.2.8
Summary: Control Clockify through Polybar
Home-page: https://github.com/woutdp/polybar-clockify
License: MIT
Keywords: polybar,clockify
Author: Wout De Puysseleir
Author-email: woutdp@gmail.com
Requires-Python: >=3.7,<4.0
Classifier: License :: OSI Approved :: MIT License
Classifier: Programming Language :: Python :: 3
Classifier: Programming Language :: Python :: 3.7
Classifier: Programming Language :: Python :: 3.8
Classifier: Programming Language :: Python :: 3.9
Requires-Dist: aiohttp[speedups] (>=3.7.3,<4.0.0)
Requires-Dist: dataclasses-json (>=0.5.2,<0.6.0)
Requires-Dist: isodate (>=0.6.0,<0.7.0)
Requires-Dist: marshmallow (>=3.10.0,<4.0.0)
Requires-Dist: pytz (>=2020.5,<2021.0)
Requires-Dist: websockets (>=8.1,<9.0)
Project-URL: Repository, https://github.com/woutdp/polybar-clockify
